astabench/__init__.py
astabench/cli.py
astabench/constants.py
astabench/config/v1.0.0-dev1.yml
astabench/config/v1.0.0.yml
astabench/evals/__init__.py
astabench/evals/_registry.py
astabench/evals/utils.py
astabench/evals/arxivdigestables/__init__.py
astabench/evals/arxivdigestables/prompts.py
astabench/evals/arxivdigestables/task.py
astabench/evals/code_diagnostics/__init__.py
astabench/evals/code_diagnostics/_sandbox_eval_code.py
astabench/evals/code_diagnostics/task.py
astabench/evals/demo/__init__.py
astabench/evals/demo/arithmetic/__init__.py
astabench/evals/demo/arithmetic/data.json
astabench/evals/demo/arithmetic/task.py
astabench/evals/demo/arithmetic/task_with_rubric.py
astabench/evals/demo/arithmetic/task_with_tools.py
astabench/evals/demo/code_execution/compose.yaml
astabench/evals/demo/code_execution/task.py
astabench/evals/discoverybench/__init__.py
astabench/evals/discoverybench/eval_utils.py
astabench/evals/discoverybench/lm_utils.py
astabench/evals/discoverybench/task.py
astabench/evals/discoverybench/task_utils.py
astabench/evals/e2e_discovery/__init__.py
astabench/evals/e2e_discovery/task.py
astabench/evals/inspect_eval_wrappers/__init__.py
astabench/evals/inspect_eval_wrappers/core_bench.py
astabench/evals/inspect_eval_wrappers/ds1000.py
astabench/evals/inspect_eval_wrappers/ds1000_splits.json
astabench/evals/labbench/__init__.py
astabench/evals/labbench/litqa2/__init__.py
astabench/evals/labbench/litqa2/task.py
astabench/evals/paper_finder/__init__.py
astabench/evals/paper_finder/datamodel.py
astabench/evals/paper_finder/eval.py
astabench/evals/paper_finder/paper_finder_utils.py
astabench/evals/paper_finder/relevance.py
astabench/evals/paper_finder/task.py
astabench/evals/sqa/__init__.py
astabench/evals/sqa/citation_eval.py
astabench/evals/sqa/precision_eval.py
astabench/evals/sqa/pydantic_models.py
astabench/evals/sqa/retry_utils.py
astabench/evals/sqa/rubric.py
astabench/evals/sqa/split_sentences.py
astabench/evals/sqa/task.py
astabench-0.3.1.dist-info/licenses/LICENSE
astabench-0.3.1.dist-info/licenses/NOTICE.txt
astabench-0.3.1.dist-info/METADATA
astabench-0.3.1.dist-info/WHEEL
astabench-0.3.1.dist-info/entry_points.txt
astabench-0.3.1.dist-info/top_level.txt
astabench-0.3.1.dist-info/RECORD
