Metadata-Version: 2.4
Name: astabench
Version: 0.3.1
Requires-Python: >=3.11
License-File: LICENSE
License-File: NOTICE.txt
Requires-Dist: inspect_ai==0.3.114
Requires-Dist: agent-eval==0.1.43
Requires-Dist: openai>=1.78.0
Requires-Dist: pydantic>=2.11.4
Requires-Dist: litellm
Requires-Dist: datasets~=3.2.0
Requires-Dist: huggingface_hub
Requires-Dist: google-genai>=1.16.1
Requires-Dist: nltk
Requires-Dist: tabulate
Requires-Dist: click==8.1.8
Requires-Dist: nora_lib-impl~=1.1.0
Requires-Dist: mcp~=1.10
Requires-Dist: httpx~=0.28.1
Requires-Dist: httpx-sse>=0.4.2
Requires-Dist: h2~=4.2.0
Requires-Dist: pandas
Requires-Dist: scipy
Requires-Dist: anthropic>=0.52.0
Requires-Dist: platformdirs
Requires-Dist: numpy
Provides-Extra: dev
Requires-Dist: black==24.2.0; extra == "dev"
Requires-Dist: isort; extra == "dev"
Requires-Dist: autoflake; extra == "dev"
Requires-Dist: pytest; extra == "dev"
Requires-Dist: pytest-asyncio; extra == "dev"
Requires-Dist: flake8==7.2.0; extra == "dev"
Requires-Dist: flake8-pyproject==1.2.3; extra == "dev"
Requires-Dist: mypy==1.15; extra == "dev"
Requires-Dist: pandas-stubs; extra == "dev"
Provides-Extra: azure
Requires-Dist: azure-ai-inference; extra == "azure"
Dynamic: license-file
